<?xml version="1.0" encoding="utf-8" ?>
<Defs>

<!--============== Manual ==============-->

<ResearchProjectDef>
    <defName>JDSMandoAndPazVizlaArmorSet</defName>
    <label>The Mando And Paz Vizla Armor set</label>
    <description>...</description>
<baseCost>2500</baseCost>
<tab>JDSTheForgetab</tab>
<techLevel>Spacer</techLevel>
<researchViewY>5</researchViewY>	<!-- up and down-->
<researchViewX>2</researchViewX>	<!-- left and right -->
		<prerequisites>
			<li>TheBlastForgeRelics</li>
		</prerequisites>
</ResearchProjectDef>

</Defs>